precis_i18n/__init__.py
precis_i18n/__init__.pyi
precis_i18n/baseclass.py
precis_i18n/baseclass.pyi
precis_i18n/bidi.py
precis_i18n/bidi.pyi
precis_i18n/codec.py
precis_i18n/codec.pyi
precis_i18n/codepointset.py
precis_i18n/codepointset.pyi
precis_i18n/context.py
precis_i18n/context.pyi
precis_i18n/derived.py
precis_i18n/derived.pyi
precis_i18n/factory.py
precis_i18n/factory.pyi
precis_i18n/profile.py
precis_i18n/profile.pyi
precis_i18n/py.typed
precis_i18n/unicode.py
precis_i18n/unicode.pyi
precis_i18n-1.1.2.dist-info/licenses/LICENSE.txt
precis_i18n-1.1.2.dist-info/METADATA
precis_i18n-1.1.2.dist-info/WHEEL
precis_i18n-1.1.2.dist-info/top_level.txt
precis_i18n-1.1.2.dist-info/zip-safe
precis_i18n-1.1.2.dist-info/RECORD
